Metadata-Version: 1.1
Name: kengste.hello.greet
Version: 0.0.1
Summary: Trying for funnn
Home-page: UNKNOWN
Author: UNKNOWN
Author-email: UNKNOWN
License: UNKNOWN
Platform: UNKNOWN
Classifier: Intended Audience :: Developers
Classifier: Programming Language :: Python
